zipcode_ng/__init__.py
zipcode_ng/main.py
zipcode_ng/states data.json
zipcode_ng-0.0.1.dist-info/LICENSE
zipcode_ng-0.0.1.dist-info/METADATA
zipcode_ng-0.0.1.dist-info/WHEEL
zipcode_ng-0.0.1.dist-info/top_level.txt
zipcode_ng-0.0.1.dist-info/RECORD
