Metadata-Version: 2.1
Name: zipcode_ng
Version: 0.0.1
Summary: information about states, local government areas (LGAs) towns and zip codes in Nigeria.
Home-page: https://github.com/awesomegoodman/zipcode-ng/tree/main/pypi
Author: Awesome Goodman
Author-email: goodman.awesome@gmail.com
Keywords: Nigerian Zip Codes,Nigerian LGAs,Nigerian Local Government Areas,Nigerian States,Nigerian Postal Codes
Classifier: Programming Language :: Python :: 3
Classifier: License :: OSI Approved :: MIT License
Classifier: Intended Audience :: Developers
Classifier: Operating System :: OS Independent
License-File: LICENSE
